{
	"configurations" : 
	[
		{
			"directories" : 
			[
				{
					"build" : ".",
					"hasInstallRule" : true,
					"jsonFile" : "directory-.-bf2fb0eff27b607d9fb3.json",
					"minimumCMakeVersion" : 
					{
						"string" : "3.12"
					},
					"projectIndex" : 0,
					"source" : ".",
					"targetIndexes" : 
					[
						0,
						1,
						2
					]
				}
			],
			"name" : "",
			"projects" : 
			[
				{
					"directoryIndexes" : 
					[
						0
					],
					"name" : "impedance_control",
					"targetIndexes" : 
					[
						0,
						1,
						2
					]
				}
			],
			"targets" : 
			[
				{
					"directoryIndex" : 0,
					"id" : "impedance_control_node::@6890427a1f51a3e7e1df",
					"jsonFile" : "target-impedance_control_node-e107c07dba4804e8dd5f.json",
					"name" : "impedance_control_node",
					"projectIndex" : 0
				},
				{
					"directoryIndex" : 0,
					"id" : "impedance_control_uninstall::@6890427a1f51a3e7e1df",
					"jsonFile" : "target-impedance_control_uninstall-373cc74da46905c06e52.json",
					"name" : "impedance_control_uninstall",
					"projectIndex" : 0
				},
				{
					"directoryIndex" : 0,
					"id" : "uninstall::@6890427a1f51a3e7e1df",
					"jsonFile" : "target-uninstall-c8bb0c7d1c0c3702c423.json",
					"name" : "uninstall",
					"projectIndex" : 0
				}
			]
		}
	],
	"kind" : "codemodel",
	"paths" : 
	{
		"build" : "/home/nocc/Desktop/3dof_rehab_arm/build/impedance_control",
		"source" : "/home/nocc/Desktop/3dof_rehab_arm/src/Control/Impedance_controller"
	},
	"version" : 
	{
		"major" : 2,
		"minor" : 3
	}
}
